tests/__init__.py
tests/models.py
ultra/__init__.py
ultra/__main__.py
ultra/database.py
ultra/log_interface.py
ultra/models.py
ultra/server.py
ultra/endpoints/__init__.py
ultra/endpoints/passes.py
ultra/endpoints/request.py
ultra/endpoints/request_id.py
ultra/endpoints/signal.py
ultra/endpoints/telemetry.py
ultra/endpoints/user.py
uniclogs_ultra-0.0.2.dist-info/METADATA
uniclogs_ultra-0.0.2.dist-info/WHEEL
uniclogs_ultra-0.0.2.dist-info/entry_points.txt
uniclogs_ultra-0.0.2.dist-info/top_level.txt
uniclogs_ultra-0.0.2.dist-info/RECORD
