Metadata-Version: 2.1
Name: uniclogs-ultra
Version: 0.0.2
Summary: A service for providing a public access interface to internal UniClOGS data.
Home-page: https://github.com/oresat/uniclogs-ultra
Author: Dmitri McGuckin
License: GPLv3
Platform: UNKNOWN
Classifier: Programming Language :: Python :: 3
Classifier: License :: OSI Approved :: GNU General Public License v3 (GPLv3)
Classifier: Topic :: Internet :: WWW/HTTP
Classifier: Operating System :: OS Independent
Classifier: Topic :: Scientific/Engineering :: Information Analysis
Requires-Python: >=3.8.5
Requires-Dist: loguru
Requires-Dist: Flask
Requires-Dist: Flask-RESTful
Requires-Dist: Flask-SQLAlchemy
Requires-Dist: psycopg2
Requires-Dist: python-dateutil
Requires-Dist: ballcosmos
Requires-Dist: pass-calculator
Provides-Extra: dev
Requires-Dist: setuptools ; extra == 'dev'
Requires-Dist: wheel ; extra == 'dev'
Requires-Dist: pytest ; extra == 'dev'
Requires-Dist: flake8 ; extra == 'dev'
Requires-Dist: twine ; extra == 'dev'
Requires-Dist: sphinx ; extra == 'dev'
Requires-Dist: sphinx-rtd-theme ; extra == 'dev'
